prince/__init__.py
prince/ca.py
prince/datasets.py
prince/famd.py
prince/gpa.py
prince/mca.py
prince/mfa.py
prince/pca.py
prince/plot.py
prince/svd.py
prince/utils.py
prince/datasets/02-resultats-par-region.csv
prince/datasets/decathlon.csv
prince/datasets/hearthstone_cards.csv
prince/datasets/per-capita-energy-stacked.csv
prince/datasets/premier_league.csv
prince/datasets/punctuation_marks.csv
prince/datasets/resultats-par-departement.csv
prince-0.16.3.dist-info/licenses/LICENSE
prince-0.16.3.dist-info/METADATA
prince-0.16.3.dist-info/WHEEL
prince-0.16.3.dist-info/top_level.txt
prince-0.16.3.dist-info/RECORD
