Metadata-Version: 2.4
Name: prince
Version: 0.16.3
Summary: Factor analysis in Python: PCA, CA, MCA, MFA, FAMD, GPA
Author-email: Max Halford <maxhalford25@gmail.com>
License-Expression: MIT
Requires-Python: >=3.10
License-File: LICENSE
Requires-Dist: scikit-learn>=1.5.1
Requires-Dist: pandas>=2.2.0
Requires-Dist: altair>=5.0.0
Provides-Extra: dev
Requires-Dist: nbconvert>=7.16.5; extra == "dev"
Requires-Dist: fbpca>=1.0; extra == "dev"
Requires-Dist: pytest>=8.3.4; extra == "dev"
Requires-Dist: ipykernel>=6.13.0; extra == "dev"
Requires-Dist: rpy2>=3.5.2; extra == "dev"
Requires-Dist: ruff>=0.8.8; extra == "dev"
Requires-Dist: xarray>=2025.1.0; extra == "dev"
Requires-Dist: pre-commit>=4.0.1; extra == "dev"
Dynamic: license-file
